timetrace/__init__.py
timetrace/timetrace.py
timetrace-0.2.3.dist-info/METADATA
timetrace-0.2.3.dist-info/WHEEL
timetrace-0.2.3.dist-info/top_level.txt
timetrace-0.2.3.dist-info/RECORD
