Metadata-Version: 2.1
Name: timetrace
Version: 0.2.3
Summary: A simple performance tracing and visualization library for Python
Author: namake
Author-email: s2222102@stu.musashino-u.ac.jp
License: MIT
Classifier: Programming Language :: Python :: 3
Classifier: License :: OSI Approved :: MIT License
Classifier: Operating System :: OS Independent
Requires-Python: >=3.6
Requires-Dist: matplotlib
